<Charakter>
  <Varianten>
    <Variante name="Beilunker Reiter">
	  <Fertigkeit name="Schusswaffen" wert="1"/>
	  <Fertigkeit name="Klingenwaffen" wert="4"/>
	  <Fertigkeit name="Selbstbeherrschung" wert="1"/>
	  <Fertigkeit name="Bildung" wert="1"/>
	  <Fertigkeit name="Heilkunde" wert="2"/>
	  <Eigenheit name="Sichere, pünktliche und unbeeinflusste Überbringung der Nachricht"/>
	  <Eigenheit name="Treue zum Dienstherr"/>
	  <Eigenheit name="Unbestechlichkeit"/>
	  <Talent name="Reiten"/>
	</Variante>
	<Variante name="Blaue Pfeile">
	  <Fertigkeit name="Bildung" wert="3"/>
	  <Fertigkeit name="Menschenkenntnis" wert="1"/>
	  <Fertigkeit name="Mythenkunde" wert="1"/>
	</Variante>
	<Variante name="Silberne Falken">
	  <Fertigkeit name="Bildung" wert="2"/>
	</Variante>
	<Variante name="Kaiserlicher Boten- und Kurierdienst">
	  <Fertigkeit name="Überleben" wert="-1"/>
	  <Talent name="Etikette"/>
	  <Vorteil name="Verbindungen" wert="40" kommentar="Offiziere/Offizielle des Mittelreichs"/>
	  <Eigenheit name="Reichstreue"/>
	  <Eigenheit name="Befehlsempfänger"/>
	  <Eigenheit name="Militärischer Geheimnisträger"/>
	</Variante>
	<Variante name="Botenläufer">
	  <Fertigkeit name="Schusswaffen" wert="-1"/>
	  <Fertigkeit name="Handgemenge" wert="2"/>
	  <Fertigkeit name="Athletik" wert="2"/>
	  <Fertigkeit name="Tierführung" wert="-3"/>
	</Variante>
	<Variante name="Zwergischer Stafettenläufer">
	  <Fertigkeit name="Handgemenge" wert="2"/>
	  <Fertigkeit name="Hiebwaffen" wert="1"/>
	  <Fertigkeit name="Athletik" wert="2"/>
	  <Fertigkeit name="Wahrnehmung" wert="2"/>
	  <Fertigkeit name="Tierführung" wert="-5"/>
	  <Fertigkeit name="Straßenkunde" wert="-1"/>
	  <Fertigkeit name="Naturkunde" wert="-1"/>
	</Variante>
  </Varianten>
  <Auswahl keine-varianten="0">
	<Fertigkeit name="Hiebwaffen" wert="1"/>
	<Fertigkeit name="Klingenwaffen" wert="1"/>
  </Auswahl>
  <Auswahl varianten="4">
    <Vorteil name="Angepasst (Wald) I"/>
    <Vorteil name="Angepasst (Schnee) I"/>
    <Vorteil name="Angepasst (Gebirge) I"/>
    <Vorteil name="Angepasst (Sumpf) I"/>
  </Auswahl>
</Charakter>